{
  "profile": [
    "+86 (10) 59173481"
  ],
  "manager": [
    "+86 (10) 59175248"
  ],
  "direct_reports": {
    "@odata.context": "https://graph.microsoft.com/v1.0/$metadata#directoryObjects",
    "value": []
  },
  "calendar_events": {
    "content": "<html>\\r\\n<head>\\r\\n<meta http-equiv=\\\"Content-Type\\\" content=\\\"text/html; charset=utf-8\\\">\\r\\n<meta name=\\\"Generator\\"
  },
  "recent_files": {
    "user": "{",
    "displayName": "Chin-Yew Lin",
    "email": "cyl@microsoft.com",
    "lastModifiedBy": "{",
    "parentReference": "{",
    "driveId": "b!ugPmZoN8O0-SXlxnyxU8N-Oi8RyRgFdPmnLl0VEvIcz51izsEQ8xR5L91n2PxQv8",
    "driveType": "business"
  },
  "mail_folders": {
    "@odata.context": "https://graph.microsoft.com/v1.0/$metadata#users('88573e4b-a91e-4334-89c2-a61178320813')/mailFolders",
    "value": [],
    "id": "AAMkAGIyM2ZkOGQ0LWEyYzQtNDdmZS1hZTE0LTU0MGU0YWIwZDVjYwAuAAAAAAB_4OkZ0z0mT6yoBB3L8TLRAQCGkPAiwOU0QZoYVb4dCok7ADk6ygCHAAA=",
    "displayName": "0 Projects",
    "parentFolderId": "AAMkAGIyM2ZkOGQ0LWEyYzQtNDdmZS1hZTE0LTU0MGU0YWIwZDVjYwAuAAAAAAB_4OkZ0z0mT6yoBB3L8TLRAQAI5eKVcQQJTq1DS1QLuzO8AAABMNKAAAA=",
    "childFolderCount": 2,
    "unreadItemCount": 0,
    "totalItemCount": 0,
    "sizeInBytes": 0,
    "isHidden": false
  },
  "groups": {
    "@odata.context": "https://graph.microsoft.com/v1.0/$metadata#directoryObjects",
    "@odata.nextLink": "\"https://graph.microsoft.com/v1.0/me/memberOf?",
    "value": [],
    "@odata.type": "#microsoft.graph.group",
    "id": "330aa9bb-4c01-43dd-9c02-f85763d7f061",
    "deletedDateTime": null,
    "classification": null
  },
  "contacts": {
    "@odata.context": "https://graph.microsoft.com/v1.0/$metadata#users('88573e4b-a91e-4334-89c2-a61178320813')/contacts",
    "value": [
      "AAMkAGIyM2ZkOGQ0LWEyYzQtNDdmZS1hZTE0LTU0MGU0YWIwZDVjYwBGAAAAAAB_4OkZ0z0mT6yoBB3L8TLRBwAI5eKVcQQJTq1DS1QLuzO8AAABMI7AAAD6QYIsVS6-QpjQwV7RhCjQAAfk8w1i"
    ],
    "@odata.etag": "W/\\\"EQAAABYAAAD6QYIsVS6/QpjQwV7RhCjQAAfcLIsK\\\"",
    "createdDateTime": "2025-09-16T01:30:03Z",
    "lastModifiedDateTime": "2025-09-16T01:30:03Z",
    "changeKey": "EQAAABYAAAD6QYIsVS6/QpjQwV7RhCjQAAfcLIsK",
    "categories": []
  }
}